jst_aicommit/api.py
jst_aicommit/database.py
jst_aicommit/exceptions.py
jst_aicommit/git.py
jst_aicommit/main.py
jst_aicommit-1.4.dist-info/LICENSE
jst_aicommit-1.4.dist-info/METADATA
jst_aicommit-1.4.dist-info/WHEEL
jst_aicommit-1.4.dist-info/entry_points.txt
jst_aicommit-1.4.dist-info/RECORD
